CHANGES
LICENSE.txt
MANIFEST.in
README.rst
makefile
pyproject.toml
setup.cfg
setup.py
doc/Makefile
doc/html/.buildinfo
doc/html/g2tools.html
doc/html/genindex.html
doc/html/index.html
doc/html/objects.inv
doc/html/overview.html
doc/html/py-modindex.html
doc/html/search.html
doc/html/searchindex.js
doc/html/.doctrees/environment.pickle
doc/html/.doctrees/g2tools.doctree
doc/html/.doctrees/index.doctree
doc/html/.doctrees/overview.doctree
doc/html/_sources/g2tools.rst.txt
doc/html/_sources/index.rst.txt
doc/html/_sources/overview.rst.txt
doc/html/_static/_sphinx_javascript_frameworks_compat.js
doc/html/_static/basic.css
doc/html/_static/dialog-note.png
doc/html/_static/dialog-seealso.png
doc/html/_static/dialog-todo.png
doc/html/_static/dialog-topic.png
doc/html/_static/dialog-warning.png
doc/html/_static/doctools.js
doc/html/_static/documentation_options.js
doc/html/_static/epub.css
doc/html/_static/file.png
doc/html/_static/footerbg.png
doc/html/_static/headerbg.png
doc/html/_static/ie6.css
doc/html/_static/jquery-3.5.1.js
doc/html/_static/jquery-3.6.0.js
doc/html/_static/jquery.js
doc/html/_static/language_data.js
doc/html/_static/middlebg.png
doc/html/_static/minus.png
doc/html/_static/plus.png
doc/html/_static/pygments.css
doc/html/_static/pyramid.css
doc/html/_static/searchtools.js
doc/html/_static/transparent.gif
doc/html/_static/underscore-1.13.1.js
doc/html/_static/underscore.js
doc/latex/Makefile
doc/latex/fncychap.sty
doc/latex/footnotehyper-sphinx.sty
doc/latex/g2tools.aux
doc/latex/g2tools.fdb_latexmk
doc/latex/g2tools.fls
doc/latex/g2tools.idx
doc/latex/g2tools.ilg
doc/latex/g2tools.ind
doc/latex/g2tools.log
doc/latex/g2tools.out
doc/latex/g2tools.tex
doc/latex/g2tools.toc
doc/latex/latexmkjarc
doc/latex/latexmkrc
doc/latex/python.ist
doc/latex/sphinx.sty
doc/latex/sphinxhighlight.sty
doc/latex/sphinxhowto.cls
doc/latex/sphinxmanual.cls
doc/latex/sphinxmulticell.sty
doc/latex/tabulary.sty
doc/latex/.doctrees/environment.pickle
src/g2tools.egg-info/PKG-INFO
src/g2tools.egg-info/SOURCES.txt
src/g2tools.egg-info/dependency_links.txt
src/g2tools.egg-info/not-zip-safe
src/g2tools.egg-info/requires.txt
src/g2tools.egg-info/top_level.txt
