Metadata-Version: 2.1
Name: g2tools
Version: 1.4.2
Summary: Utilities for muon g-2 analyses in lattice QCD.
Home-page: https://github.com/gplepage/g2tools
Author: G. Peter Lepage
Author-email: g.p.lepage@cornell.edu
License: GPLv3
Requires-Python: >=2.7
License-File: LICENSE.txt
